[
  {
    "userID": "100073702260466",
    "name": "Md mirajul 卝ইসলামヅ",
    "gender": 2,
    "vanity": "miraj01337229908",
    "exp": 163,
    "money": 0,
    "banned": {},
    "settings": {},
    "data": {},
    "createdAt": "2025-10-19T14:21:08.015Z",
    "updatedAt": "2025-10-20T06:42:56.796Z"
  },
  {
    "userID": "61572981141995",
    "name": "Antu Das",
    "gender": 2,
    "vanity": "antu.das.27182",
    "exp": 38,
    "money": 0,
    "banned": {},
    "settings": {},
    "data": {},
    "createdAt": "2025-10-19T14:21:26.063Z",
    "updatedAt": "2025-10-20T06:20:00.433Z"
  },
  {
    "userID": "100058751258050",
    "name": "S M Sohan",
    "gender": 2,
    "vanity": "s.m.sohan.826773",
    "exp": 9,
    "money": 0,
    "banned": {},
    "settings": {},
    "data": {},
    "createdAt": "2025-10-19T14:21:51.903Z",
    "updatedAt": "2025-10-20T04:56:33.759Z"
  },
  {
    "userID": "61563849983537",
    "name": "Seno Rîta",
    "gender": 1,
    "vanity": "ni.shi.87444",
    "exp": 1,
    "money": 0,
    "banned": {},
    "settings": {},
    "data": {},
    "createdAt": "2025-10-19T14:21:55.577Z",
    "updatedAt": "2025-10-19T14:21:55.603Z"
  },
  {
    "userID": "61575135956361",
    "name": "শূন্য আকাশ",
    "gender": 2,
    "vanity": "sun.ya.chomya",
    "exp": 179,
    "money": 0,
    "banned": {},
    "settings": {},
    "data": {},
    "createdAt": "2025-10-19T14:26:03.443Z",
    "updatedAt": "2025-10-20T06:59:25.361Z"
  },
  {
    "userID": "100080458885215",
    "name": "MD Shariful Hasan",
    "gender": 2,
    "vanity": "md.shariful.hasan.332216",
    "exp": 40,
    "money": 0,
    "banned": {},
    "settings": {},
    "data": {},
    "createdAt": "2025-10-19T14:34:05.865Z",
    "updatedAt": "2025-10-20T06:00:54.554Z"
  },
  {
    "userID": "100066867630344",
    "name": "Mâybê Nx",
    "gender": 2,
    "vanity": "nx210.is.back",
    "exp": 257,
    "money": 100066867630444,
    "banned": {},
    "settings": {},
    "data": {
      "lastTimeGetReward": "20/10/2025"
    },
    "createdAt": "2025-10-19T14:35:21.989Z",
    "updatedAt": "2025-10-20T07:02:26.815Z"
  },
  {
    "userID": "100095135606898",
    "name": "Suvo Molla",
    "gender": 2,
    "vanity": "suvo.molla.99814",
    "exp": 27,
    "money": 0,
    "banned": {},
    "settings": {},
    "data": {},
    "createdAt": "2025-10-19T14:35:28.979Z",
    "updatedAt": "2025-10-20T00:46:00.887Z"
  },
  {
    "userID": "61550720669277",
    "name": "Itz Abrar",
    "gender": 2,
    "vanity": "itz.abrar.909616",
    "exp": 4,
    "money": 0,
    "banned": {},
    "settings": {},
    "data": {},
    "createdAt": "2025-10-19T14:36:17.884Z",
    "updatedAt": "2025-10-20T05:40:02.755Z"
  },
  {
    "userID": "100092488789729",
    "name": "Max Mafuz",
    "gender": 2,
    "vanity": "",
    "exp": 117,
    "money": 0,
    "banned": {},
    "settings": {},
    "data": {},
    "createdAt": "2025-10-19T14:36:40.513Z",
    "updatedAt": "2025-10-20T05:49:56.409Z"
  },
  {
    "userID": "61579160603283",
    "name": "Arisha Islam",
    "gender": 1,
    "vanity": "",
    "exp": 78,
    "money": 0,
    "banned": {},
    "settings": {},
    "data": {},
    "createdAt": "2025-10-19T14:38:10.400Z",
    "updatedAt": "2025-10-20T06:56:52.667Z"
  },
  {
    "userID": "61565116571898",
    "name": "Makhnun Sultana Samu",
    "gender": 1,
    "vanity": "noyona.x.samia",
    "exp": 63,
    "money": 0,
    "banned": {},
    "settings": {},
    "data": {},
    "createdAt": "2025-10-19T14:38:53.428Z",
    "updatedAt": "2025-10-19T14:54:02.176Z"
  },
  {
    "userID": "61579583510643",
    "name": "Jaegyeon Na",
    "gender": 2,
    "vanity": "",
    "exp": 0,
    "money": 0,
    "banned": {},
    "settings": {},
    "data": {},
    "updatedAt": "2025-10-19T14:38:57.908Z",
    "createdAt": "2025-10-19T14:38:57.908Z"
  },
  {
    "userID": "100089055783144",
    "name": "Sadika Sara",
    "gender": 1,
    "vanity": "",
    "exp": 425,
    "money": 0,
    "banned": {},
    "settings": {},
    "data": {},
    "createdAt": "2025-10-19T14:38:58.428Z",
    "updatedAt": "2025-10-20T07:02:27.242Z"
  },
  {
    "userID": "100089210962332",
    "name": "Meaw Ariyan",
    "gender": 2,
    "vanity": "meaw.ariyan",
    "exp": 22,
    "money": 0,
    "banned": {},
    "settings": {},
    "data": {},
    "createdAt": "2025-10-19T14:39:22.533Z",
    "updatedAt": "2025-10-20T05:40:34.155Z"
  },
  {
    "userID": "100088735041597",
    "name": "Nirob Khan",
    "gender": 2,
    "vanity": "nirob.khan.457297",
    "exp": 12,
    "money": 0,
    "banned": {},
    "settings": {},
    "data": {},
    "createdAt": "2025-10-19T14:41:04.783Z",
    "updatedAt": "2025-10-20T05:46:57.517Z"
  },
  {
    "userID": "61554931754600",
    "name": "অবুঝ ছেলে পাভেল ম্যাক্স",
    "gender": 2,
    "vanity": "abujha.chele.572223",
    "exp": 41,
    "money": 0,
    "banned": {},
    "settings": {},
    "data": {},
    "createdAt": "2025-10-19T14:42:23.342Z",
    "updatedAt": "2025-10-20T06:43:22.900Z"
  },
  {
    "userID": "61575249832843",
    "name": "Vortex L. Kiran",
    "gender": 2,
    "vanity": "",
    "exp": 40,
    "money": 0,
    "banned": {},
    "settings": {},
    "data": {},
    "createdAt": "2025-10-19T14:45:07.956Z",
    "updatedAt": "2025-10-20T04:34:15.529Z"
  },
  {
    "userID": "61581808689990",
    "name": "Jerin Islam",
    "gender": 1,
    "vanity": "",
    "exp": 2,
    "money": 0,
    "banned": {},
    "settings": {},
    "data": {},
    "createdAt": "2025-10-19T14:53:15.883Z",
    "updatedAt": "2025-10-19T14:55:20.571Z"
  },
  {
    "userID": "61580171807221",
    "name": "Iyasmi Islam",
    "gender": 1,
    "vanity": "",
    "exp": 5,
    "money": 0,
    "banned": {},
    "settings": {},
    "data": {},
    "createdAt": "2025-10-19T15:05:51.862Z",
    "updatedAt": "2025-10-19T15:13:11.356Z"
  },
  {
    "userID": "61574711814933",
    "name": "Sushil Shino",
    "gender": 1,
    "vanity": "sushil.shino",
    "exp": 7,
    "money": 0,
    "banned": {},
    "settings": {},
    "data": {},
    "createdAt": "2025-10-19T15:09:23.419Z",
    "updatedAt": "2025-10-19T15:12:55.145Z"
  },
  {
    "userID": "100093975048132",
    "name": "Gojo Satoru",
    "gender": 2,
    "vanity": "nishanxpain",
    "exp": 2,
    "money": 0,
    "banned": {},
    "settings": {},
    "data": {},
    "createdAt": "2025-10-19T15:15:08.073Z",
    "updatedAt": "2025-10-20T05:03:06.342Z"
  },
  {
    "userID": "61580896247839",
    "name": "Nusrat Jahan",
    "gender": 1,
    "vanity": "",
    "exp": 5,
    "money": 0,
    "banned": {},
    "settings": {},
    "data": {},
    "createdAt": "2025-10-19T15:16:02.774Z",
    "updatedAt": "2025-10-19T16:15:36.562Z"
  },
  {
    "userID": "61571064654271",
    "name": "Sinthiya Islan",
    "gender": 1,
    "vanity": "sinthiya.islan.2025",
    "exp": 159,
    "money": 0,
    "banned": {},
    "settings": {},
    "data": {},
    "createdAt": "2025-10-19T15:21:38.256Z",
    "updatedAt": "2025-10-20T07:02:05.894Z"
  },
  {
    "userID": "100049295749147",
    "name": "Ahammed Siyam",
    "gender": 2,
    "vanity": "nilarjamai0.1",
    "exp": 6,
    "money": 0,
    "banned": {},
    "settings": {},
    "data": {},
    "createdAt": "2025-10-19T15:23:49.314Z",
    "updatedAt": "2025-10-20T02:46:51.146Z"
  },
  {
    "userID": "61559035540042",
    "name": "Fahim Islam Shaan",
    "gender": 2,
    "vanity": "fahim.islam.shaan.2024",
    "exp": 8,
    "money": 0,
    "banned": {},
    "settings": {},
    "data": {},
    "createdAt": "2025-10-19T15:27:51.870Z",
    "updatedAt": "2025-10-20T05:00:45.661Z"
  },
  {
    "userID": "61552972888435",
    "name": "Jannat Khan",
    "gender": 1,
    "vanity": "",
    "exp": 10,
    "money": 0,
    "banned": {},
    "settings": {},
    "data": {},
    "createdAt": "2025-10-19T15:28:15.319Z",
    "updatedAt": "2025-10-19T15:28:50.189Z"
  },
  {
    "userID": "61575207380285",
    "name": "Ay Aan",
    "gender": 2,
    "vanity": "ay.aan.476159",
    "exp": 34,
    "money": 0,
    "banned": {},
    "settings": {},
    "data": {},
    "createdAt": "2025-10-19T15:31:38.267Z",
    "updatedAt": "2025-10-20T05:28:43.987Z"
  },
  {
    "userID": "61580107963263",
    "name": "Rom Jan",
    "gender": 2,
    "vanity": "",
    "exp": 18,
    "money": 0,
    "banned": {},
    "settings": {},
    "data": {},
    "createdAt": "2025-10-19T15:38:38.722Z",
    "updatedAt": "2025-10-20T07:01:58.311Z"
  },
  {
    "userID": "100084479623569",
    "name": "Ari Y AN",
    "gender": 2,
    "vanity": "ariyan7089",
    "exp": 0,
    "money": 0,
    "banned": {},
    "settings": {},
    "data": {},
    "updatedAt": "2025-10-19T15:41:07.241Z",
    "createdAt": "2025-10-19T15:41:07.241Z"
  },
  {
    "userID": "61559043968142",
    "name": "Ahmmed'z Mahin",
    "gender": 2,
    "vanity": "ahmmed.z.mahin",
    "exp": 32,
    "money": 0,
    "banned": {},
    "settings": {},
    "data": {},
    "createdAt": "2025-10-19T15:44:51.623Z",
    "updatedAt": "2025-10-20T05:27:21.304Z"
  },
  {
    "userID": "61558945902622",
    "name": "Prapti Roy",
    "gender": 1,
    "vanity": "prapti.roy.nayek",
    "exp": 4,
    "money": 0,
    "banned": {},
    "settings": {},
    "data": {},
    "createdAt": "2025-10-19T15:45:57.176Z",
    "updatedAt": "2025-10-19T20:15:12.942Z"
  },
  {
    "userID": "61569869610229",
    "name": "আম্মু আব্বুর আদরের রাজপুত্র",
    "gender": 2,
    "vanity": "",
    "exp": 11,
    "money": 0,
    "banned": {},
    "settings": {},
    "data": {},
    "createdAt": "2025-10-19T15:50:25.067Z",
    "updatedAt": "2025-10-20T05:58:38.259Z"
  },
  {
    "userID": "61579641237836",
    "name": "Eren Rest'ricted ま",
    "gender": 2,
    "vanity": "",
    "exp": 12,
    "money": 0,
    "banned": {},
    "settings": {},
    "data": {},
    "createdAt": "2025-10-19T15:56:47.772Z",
    "updatedAt": "2025-10-20T05:59:48.048Z"
  },
  {
    "userID": "100041714220207",
    "name": "Jo Han",
    "gender": 2,
    "vanity": "sahadat.hossin.92317121",
    "exp": 1,
    "money": 0,
    "banned": {},
    "settings": {},
    "data": {},
    "createdAt": "2025-10-19T16:06:37.400Z",
    "updatedAt": "2025-10-19T16:06:38.359Z"
  },
  {
    "userID": "100079258446314",
    "name": "Md An Ik",
    "gender": 2,
    "vanity": "md.an.ik.605396",
    "exp": 2,
    "money": 0,
    "banned": {},
    "settings": {},
    "data": {},
    "createdAt": "2025-10-19T16:08:35.514Z",
    "updatedAt": "2025-10-20T06:37:40.977Z"
  },
  {
    "userID": "100046194189374",
    "name": "Samiul Islam Middya",
    "gender": 2,
    "vanity": "samiulislam.middya.9",
    "exp": 10,
    "money": 0,
    "banned": {},
    "settings": {},
    "data": {},
    "createdAt": "2025-10-19T16:15:12.757Z",
    "updatedAt": "2025-10-20T05:59:39.149Z"
  },
  {
    "userID": "61557852974898",
    "name": "সিঙ্গেল স্বাধীন",
    "gender": 1,
    "vanity": "sbadhina.isalama.jibana",
    "exp": 28,
    "money": 0,
    "banned": {},
    "settings": {},
    "data": {},
    "createdAt": "2025-10-19T16:20:42.786Z",
    "updatedAt": "2025-10-20T02:29:42.158Z"
  },
  {
    "userID": "61560932571465",
    "name": "Md Roman",
    "gender": 2,
    "vanity": "md.roman.309990",
    "exp": 2,
    "money": 0,
    "banned": {},
    "settings": {},
    "data": {},
    "createdAt": "2025-10-19T16:20:49.088Z",
    "updatedAt": "2025-10-20T06:59:34.777Z"
  },
  {
    "userID": "61572395725798",
    "name": "Zafrin Islam",
    "gender": 1,
    "vanity": "fatema.islam.979647",
    "exp": 2,
    "money": 0,
    "banned": {},
    "settings": {},
    "data": {},
    "createdAt": "2025-10-19T16:22:58.455Z",
    "updatedAt": "2025-10-19T16:23:07.653Z"
  },
  {
    "userID": "100073556190750",
    "name": "Khatheza Aktar",
    "gender": 1,
    "vanity": "khatheza.aktar.2024",
    "exp": 0,
    "money": 0,
    "banned": {},
    "settings": {},
    "data": {},
    "updatedAt": "2025-10-19T16:25:22.652Z",
    "createdAt": "2025-10-19T16:25:22.652Z"
  },
  {
    "userID": "100047993198293",
    "name": "Jeon Ruhi",
    "gender": 1,
    "vanity": "jeon.ruhi.45135",
    "exp": 54,
    "money": 0,
    "banned": {},
    "settings": {},
    "data": {},
    "createdAt": "2025-10-19T16:28:44.637Z",
    "updatedAt": "2025-10-20T05:38:16.656Z"
  },
  {
    "userID": "61576744571129",
    "name": "It'z Ovi",
    "gender": 2,
    "vanity": "",
    "exp": 4,
    "money": 0,
    "banned": {},
    "settings": {},
    "data": {},
    "createdAt": "2025-10-19T16:29:23.055Z",
    "updatedAt": "2025-10-20T00:46:22.454Z"
  },
  {
    "userID": "61578589933640",
    "name": "পিচ্চি বউ",
    "gender": 1,
    "vanity": "",
    "exp": 1,
    "money": 0,
    "banned": {},
    "settings": {},
    "data": {},
    "createdAt": "2025-10-19T16:40:30.168Z",
    "updatedAt": "2025-10-19T16:40:30.185Z"
  },
  {
    "userID": "61575281563625",
    "name": "Rafi Vai",
    "gender": 2,
    "vanity": "rafi10029",
    "exp": 2,
    "money": 0,
    "banned": {},
    "settings": {},
    "data": {},
    "createdAt": "2025-10-19T16:42:31.510Z",
    "updatedAt": "2025-10-19T16:42:35.398Z"
  },
  {
    "userID": "100087913354897",
    "name": "Ritik Gurau",
    "gender": 2,
    "vanity": "before0silent",
    "exp": 1,
    "money": 0,
    "banned": {},
    "settings": {},
    "data": {},
    "createdAt": "2025-10-19T16:43:39.746Z",
    "updatedAt": "2025-10-19T16:43:39.768Z"
  },
  {
    "userID": "61553110065257",
    "name": "Itz Real Fahim",
    "gender": 1,
    "vanity": "itz.real.fahim",
    "exp": 6,
    "money": 0,
    "banned": {},
    "settings": {},
    "data": {},
    "createdAt": "2025-10-19T16:47:10.549Z",
    "updatedAt": "2025-10-20T07:02:07.357Z"
  },
  {
    "userID": "61575202615476",
    "name": "Tomodachi Dayo",
    "gender": 2,
    "vanity": "tomodachi.dayo.493363",
    "exp": 0,
    "money": 0,
    "banned": {},
    "settings": {},
    "data": {},
    "updatedAt": "2025-10-19T16:50:39.442Z",
    "createdAt": "2025-10-19T16:50:39.442Z"
  },
  {
    "userID": "61557691140719",
    "name": "Sharif Vhi Jan",
    "gender": 2,
    "vanity": "atikul.khan.394299",
    "exp": 1,
    "money": 0,
    "banned": {},
    "settings": {},
    "data": {},
    "createdAt": "2025-10-19T16:50:45.548Z",
    "updatedAt": "2025-10-19T16:50:46.457Z"
  },
  {
    "userID": "100030542676272",
    "name": "Miraj Hossain",
    "gender": 2,
    "vanity": "miraj.hossain.82",
    "exp": 5,
    "money": 0,
    "banned": {},
    "settings": {},
    "data": {},
    "createdAt": "2025-10-19T16:51:13.761Z",
    "updatedAt": "2025-10-20T06:06:28.257Z"
  },
  {
    "userID": "100068828425308",
    "name": "AB IR",
    "gender": 2,
    "vanity": "abir.abdullah.10420",
    "exp": 14,
    "money": 0,
    "banned": {},
    "settings": {},
    "data": {},
    "createdAt": "2025-10-19T16:51:37.112Z",
    "updatedAt": "2025-10-20T06:33:45.755Z"
  },
  {
    "userID": "61579737849644",
    "name": "Megh Balika",
    "gender": 1,
    "vanity": "",
    "exp": 3,
    "money": 0,
    "banned": {},
    "settings": {},
    "data": {},
    "createdAt": "2025-10-19T16:51:37.705Z",
    "updatedAt": "2025-10-19T16:51:47.135Z"
  },
  {
    "userID": "61581479738884",
    "name": "누하쉬",
    "gender": 1,
    "vanity": "jeonnuhas",
    "exp": 116,
    "money": 0,
    "banned": {},
    "settings": {},
    "data": {},
    "createdAt": "2025-10-19T16:52:40.532Z",
    "updatedAt": "2025-10-20T06:49:39.432Z"
  },
  {
    "userID": "61579229701405",
    "name": "Cʜoc ʞʟʌtƴ 💙🪻🪽",
    "gender": 1,
    "vanity": "",
    "exp": 2,
    "money": 0,
    "banned": {},
    "settings": {},
    "data": {},
    "createdAt": "2025-10-19T16:53:12.185Z",
    "updatedAt": "2025-10-19T16:53:16.855Z"
  },
  {
    "userID": "61578964664088",
    "name": "Ayshu MOni",
    "gender": 1,
    "vanity": "",
    "exp": 7,
    "money": 0,
    "banned": {},
    "settings": {},
    "data": {},
    "createdAt": "2025-10-19T16:54:41.136Z",
    "updatedAt": "2025-10-19T17:01:22.816Z"
  },
  {
    "userID": "100026509416024",
    "name": "Romjan Ali",
    "gender": 2,
    "vanity": "romjan.ali.338224",
    "exp": 20,
    "money": 0,
    "banned": {},
    "settings": {},
    "data": {},
    "createdAt": "2025-10-19T16:54:53.497Z",
    "updatedAt": "2025-10-20T03:31:11.816Z"
  },
  {
    "userID": "100093633406916",
    "name": "মে্ঁঘে্ঁ ঢা্ঁকা্ঁ তা্ঁরা্ঁ",
    "gender": 1,
    "vanity": "",
    "exp": 0,
    "money": 0,
    "banned": {},
    "settings": {},
    "data": {},
    "updatedAt": "2025-10-19T16:58:22.243Z",
    "createdAt": "2025-10-19T16:58:22.243Z"
  },
  {
    "userID": "61573782090608",
    "name": "Rahim Hasan",
    "gender": 2,
    "vanity": "rahim.hasan.938162",
    "exp": 3,
    "money": 0,
    "banned": {},
    "settings": {},
    "data": {},
    "createdAt": "2025-10-19T17:08:47.090Z",
    "updatedAt": "2025-10-20T06:32:40.688Z"
  },
  {
    "userID": "61578265715380",
    "name": "NO Bi Ta",
    "gender": 2,
    "vanity": "",
    "exp": 33,
    "money": 0,
    "banned": {},
    "settings": {},
    "data": {},
    "createdAt": "2025-10-19T17:15:56.340Z",
    "updatedAt": "2025-10-20T03:55:16.529Z"
  },
  {
    "userID": "100092157797651",
    "name": "Emon Hossain",
    "gender": 2,
    "vanity": "emon.hossain.506249",
    "exp": 1,
    "money": 0,
    "banned": {},
    "settings": {},
    "data": {},
    "createdAt": "2025-10-19T17:29:57.280Z",
    "updatedAt": "2025-10-19T17:29:57.360Z"
  },
  {
    "userID": "100030475590259",
    "name": "Md Nihan",
    "gender": 2,
    "vanity": "area.akter.1",
    "exp": 2,
    "money": 0,
    "banned": {},
    "settings": {},
    "data": {},
    "createdAt": "2025-10-19T17:30:15.820Z",
    "updatedAt": "2025-10-19T18:09:41.072Z"
  },
  {
    "userID": "61556819367914",
    "name": "Tomie Kawakami",
    "gender": 1,
    "vanity": "tomie.kawakami.955579",
    "exp": 1,
    "money": 0,
    "banned": {},
    "settings": {},
    "data": {},
    "createdAt": "2025-10-19T17:33:27.247Z",
    "updatedAt": "2025-10-19T17:33:27.280Z"
  },
  {
    "userID": "100078718613342",
    "name": "Hiya Aktar Snigdha",
    "gender": 1,
    "vanity": "hiya.aktar.snigdha",
    "exp": 19,
    "money": 0,
    "banned": {},
    "settings": {},
    "data": {},
    "createdAt": "2025-10-19T17:33:37.501Z",
    "updatedAt": "2025-10-20T04:02:48.872Z"
  },
  {
    "userID": "61581366555316",
    "name": "Jiniya Islam Jara",
    "gender": 2,
    "vanity": "",
    "exp": 9,
    "money": 0,
    "banned": {},
    "settings": {},
    "data": {},
    "createdAt": "2025-10-19T17:34:31.809Z",
    "updatedAt": "2025-10-19T17:39:29.719Z"
  },
  {
    "userID": "100020917118831",
    "name": "Riaz Mohammad",
    "gender": 2,
    "vanity": "riaz.mohammad.chowdhory",
    "exp": 2,
    "money": 0,
    "banned": {},
    "settings": {},
    "data": {},
    "createdAt": "2025-10-19T17:34:47.938Z",
    "updatedAt": "2025-10-19T17:39:47.026Z"
  },
  {
    "userID": "61573411652771",
    "name": "Samiya Akter Roza",
    "gender": 1,
    "vanity": "",
    "exp": 1,
    "money": 0,
    "banned": {},
    "settings": {},
    "data": {},
    "createdAt": "2025-10-19T17:35:07.253Z",
    "updatedAt": "2025-10-19T17:35:07.269Z"
  },
  {
    "userID": "61576203429618",
    "name": "Hope J",
    "gender": 2,
    "vanity": "",
    "exp": 2,
    "money": 0,
    "banned": {},
    "settings": {},
    "data": {},
    "createdAt": "2025-10-19T17:39:17.226Z",
    "updatedAt": "2025-10-19T17:40:05.571Z"
  },
  {
    "userID": "61579355619783",
    "name": "Jannat Rahman",
    "gender": 1,
    "vanity": "",
    "exp": 1,
    "money": 0,
    "banned": {},
    "settings": {},
    "data": {},
    "createdAt": "2025-10-19T17:39:49.691Z",
    "updatedAt": "2025-10-19T17:39:49.714Z"
  },
  {
    "userID": "100073222834221",
    "name": "অবুজ ছেলে",
    "gender": 2,
    "vanity": "abuja.chele.771723",
    "exp": 1,
    "money": 0,
    "banned": {},
    "settings": {},
    "data": {},
    "createdAt": "2025-10-19T17:56:03.178Z",
    "updatedAt": "2025-10-19T17:56:03.196Z"
  },
  {
    "userID": "61578238877151",
    "name": "Cursed'Bloom羅",
    "gender": 1,
    "vanity": "",
    "exp": 1,
    "money": 0,
    "banned": {},
    "settings": {},
    "data": {},
    "createdAt": "2025-10-19T17:59:12.040Z",
    "updatedAt": "2025-10-19T17:59:12.056Z"
  },
  {
    "userID": "100086728620936",
    "name": "Nipa Hossain",
    "gender": 1,
    "vanity": "ayesha.hossain.ayesha.2024",
    "exp": 25,
    "money": 0,
    "banned": {},
    "settings": {},
    "data": {},
    "createdAt": "2025-10-19T18:04:32.514Z",
    "updatedAt": "2025-10-20T05:08:34.375Z"
  },
  {
    "userID": "61566182766632",
    "name": "Md Ariyan Khan",
    "gender": 2,
    "vanity": "md.ariyan.khan.401327",
    "exp": 0,
    "money": 0,
    "banned": {},
    "settings": {},
    "data": {},
    "updatedAt": "2025-10-19T18:05:05.349Z",
    "createdAt": "2025-10-19T18:05:05.349Z"
  },
  {
    "userID": "100027818117769",
    "name": "IB SA",
    "gender": 2,
    "vanity": "marshmelo.marshmelo.14",
    "exp": 11,
    "money": 0,
    "banned": {},
    "settings": {},
    "data": {},
    "createdAt": "2025-10-19T18:05:06.435Z",
    "updatedAt": "2025-10-20T06:31:06.700Z"
  },
  {
    "userID": "100079604031768",
    "name": "গল্প কথা",
    "gender": 1,
    "vanity": "galpa.katha.63415",
    "exp": 2,
    "money": 0,
    "banned": {},
    "settings": {},
    "data": {},
    "createdAt": "2025-10-19T18:07:09.375Z",
    "updatedAt": "2025-10-19T18:08:34.211Z"
  },
  {
    "userID": "61572801440030",
    "name": "Tamim Ahmed",
    "gender": 2,
    "vanity": "tamim.ahmed.459150",
    "exp": 1,
    "money": 0,
    "banned": {},
    "settings": {},
    "data": {},
    "createdAt": "2025-10-19T18:07:09.989Z",
    "updatedAt": "2025-10-19T18:07:10.006Z"
  },
  {
    "userID": "100002449842401",
    "name": "S M Shakander",
    "gender": 2,
    "vanity": "rubel.akas.33",
    "exp": 1,
    "money": 0,
    "banned": {},
    "settings": {},
    "data": {},
    "createdAt": "2025-10-19T18:07:32.264Z",
    "updatedAt": "2025-10-19T18:07:32.357Z"
  },
  {
    "userID": "100072258193776",
    "name": "Reactor King",
    "gender": 2,
    "vanity": "reactor.king.360203",
    "exp": 1,
    "money": 0,
    "banned": {},
    "settings": {},
    "data": {},
    "createdAt": "2025-10-19T18:11:06.675Z",
    "updatedAt": "2025-10-19T18:16:59.092Z"
  },
  {
    "userID": "100068327589698",
    "name": "Md Anowar Hossain",
    "gender": 2,
    "vanity": "md.anowar.hossain.514696",
    "exp": 2,
    "money": 0,
    "banned": {},
    "settings": {},
    "data": {},
    "createdAt": "2025-10-19T18:11:39.662Z",
    "updatedAt": "2025-10-19T18:11:50.665Z"
  },
  {
    "userID": "61564187469067",
    "name": "রুপ নগরের রাজকুমারী",
    "gender": 1,
    "vanity": "",
    "exp": 4,
    "money": 0,
    "banned": {},
    "settings": {},
    "data": {},
    "createdAt": "2025-10-19T18:12:29.866Z",
    "updatedAt": "2025-10-19T19:07:03.212Z"
  },
  {
    "userID": "100060729444461",
    "name": "পি্ঁচ্চি্ঁ ব্ঁউ্ঁ তা্ঁহ্ঁ",
    "gender": 2,
    "vanity": "pi.mcci.m.bmu.m.ta.mhm.695882",
    "exp": 2,
    "money": 0,
    "banned": {},
    "settings": {},
    "data": {},
    "createdAt": "2025-10-19T18:13:29.278Z",
    "updatedAt": "2025-10-19T18:14:54.771Z"
  },
  {
    "userID": "61573506735607",
    "name": "Tennysion Here",
    "gender": 2,
    "vanity": "",
    "exp": 26,
    "money": 0,
    "banned": {},
    "settings": {},
    "data": {},
    "createdAt": "2025-10-19T18:33:16.096Z",
    "updatedAt": "2025-10-20T06:57:48.575Z"
  },
  {
    "userID": "61573422434127",
    "name": "Zannat Rehman",
    "gender": 1,
    "vanity": "",
    "exp": 0,
    "money": 0,
    "banned": {},
    "settings": {},
    "data": {},
    "updatedAt": "2025-10-19T18:51:36.700Z",
    "createdAt": "2025-10-19T18:51:36.700Z"
  },
  {
    "userID": "61576658795403",
    "name": "Abdullah Exists",
    "gender": 2,
    "vanity": "",
    "exp": 0,
    "money": 0,
    "banned": {},
    "settings": {},
    "data": {},
    "updatedAt": "2025-10-19T18:58:37.834Z",
    "createdAt": "2025-10-19T18:58:37.834Z"
  },
  {
    "userID": "61580889675145",
    "name": "Jeon Sumi",
    "gender": 2,
    "vanity": "",
    "exp": 8,
    "money": 0,
    "banned": {},
    "settings": {},
    "data": {},
    "createdAt": "2025-10-19T19:01:07.133Z",
    "updatedAt": "2025-10-20T06:54:43.054Z"
  },
  {
    "userID": "61560272968285",
    "name": "Talha Jubayer",
    "gender": 2,
    "vanity": "talha.jubayer.313292",
    "exp": 17,
    "money": 0,
    "banned": {},
    "settings": {},
    "data": {},
    "createdAt": "2025-10-19T19:33:25.264Z",
    "updatedAt": "2025-10-20T06:56:10.655Z"
  },
  {
    "userID": "61566699801727",
    "name": "Jeon Ālîyā",
    "gender": 1,
    "vanity": "ew.r.zara.944823",
    "exp": 2,
    "money": 0,
    "banned": {},
    "settings": {},
    "data": {},
    "createdAt": "2025-10-19T19:42:14.644Z",
    "updatedAt": "2025-10-20T03:31:09.356Z"
  },
  {
    "userID": "100080318533313",
    "name": "Er An I",
    "gender": 1,
    "vanity": "",
    "exp": 0,
    "money": 0,
    "banned": {},
    "settings": {},
    "data": {},
    "updatedAt": "2025-10-19T20:10:44.106Z",
    "createdAt": "2025-10-19T20:10:44.106Z"
  },
  {
    "userID": "100011050847610",
    "name": "মেয়েদের মজা দেই",
    "gender": 2,
    "vanity": "md.giadh",
    "exp": 1,
    "money": 0,
    "banned": {},
    "settings": {},
    "data": {},
    "createdAt": "2025-10-19T22:33:22.276Z",
    "updatedAt": "2025-10-19T22:33:22.291Z"
  },
  {
    "userID": "100092572182550",
    "name": "Manik Shiekh",
    "gender": 2,
    "vanity": "yourmanik20",
    "exp": 17,
    "money": 0,
    "banned": {},
    "settings": {},
    "data": {},
    "createdAt": "2025-10-19T23:27:52.496Z",
    "updatedAt": "2025-10-20T04:46:08.804Z"
  },
  {
    "userID": "61560168304544",
    "name": "Jeon Tithi",
    "gender": 1,
    "vanity": "abhimani.mana.957044",
    "exp": 5,
    "money": 0,
    "banned": {},
    "settings": {},
    "data": {},
    "createdAt": "2025-10-20T00:30:08.413Z",
    "updatedAt": "2025-10-20T00:35:56.357Z"
  },
  {
    "userID": "61580863407308",
    "name": "Ng Phương Linh",
    "gender": 1,
    "vanity": "",
    "exp": 75,
    "money": 0,
    "banned": {},
    "settings": {},
    "data": {},
    "createdAt": "2025-10-20T00:36:09.124Z",
    "updatedAt": "2025-10-20T01:32:45.713Z"
  },
  {
    "userID": "61571292260614",
    "name": "Golden Maknae",
    "gender": 2,
    "vanity": "",
    "exp": 20,
    "money": 0,
    "banned": {},
    "settings": {},
    "data": {},
    "createdAt": "2025-10-20T00:37:02.556Z",
    "updatedAt": "2025-10-20T01:56:20.557Z"
  },
  {
    "userID": "61574882636910",
    "name": "ধ্বংসবতী ধ্বংসবতী",
    "gender": 1,
    "vanity": "",
    "exp": 12,
    "money": 0,
    "banned": {},
    "settings": {},
    "data": {},
    "createdAt": "2025-10-20T00:40:57.197Z",
    "updatedAt": "2025-10-20T01:15:02.061Z"
  },
  {
    "userID": "100087653230769",
    "name": "Lamiya Aktar",
    "gender": 2,
    "vanity": "",
    "exp": 17,
    "money": 0,
    "banned": {},
    "settings": {},
    "data": {},
    "createdAt": "2025-10-20T00:46:05.939Z",
    "updatedAt": "2025-10-20T01:07:10.170Z"
  },
  {
    "userID": "100094252909660",
    "name": "Sk Rafin",
    "gender": 1,
    "vanity": "sk.rafin.470815",
    "exp": 18,
    "money": 0,
    "banned": {},
    "settings": {},
    "data": {},
    "createdAt": "2025-10-20T00:46:47.683Z",
    "updatedAt": "2025-10-20T06:29:44.044Z"
  },
  {
    "userID": "100010507727288",
    "name": "Mon Ke Palo",
    "gender": 2,
    "vanity": "",
    "exp": 74,
    "money": 0,
    "banned": {},
    "settings": {},
    "data": {},
    "createdAt": "2025-10-20T00:53:13.954Z",
    "updatedAt": "2025-10-20T06:46:21.068Z"
  },
  {
    "userID": "61561108683688",
    "name": "MD Siam Hossain",
    "gender": 2,
    "vanity": "md.siam.hossain.466404",
    "exp": 1,
    "money": 0,
    "banned": {},
    "settings": {},
    "data": {},
    "createdAt": "2025-10-20T00:59:26.962Z",
    "updatedAt": "2025-10-20T00:59:26.980Z"
  },
  {
    "userID": "61576406363046",
    "name": "Nusrat Jahan",
    "gender": 1,
    "vanity": "",
    "exp": 4,
    "money": 0,
    "banned": {},
    "settings": {},
    "data": {},
    "createdAt": "2025-10-20T01:09:04.292Z",
    "updatedAt": "2025-10-20T06:41:33.625Z"
  },
  {
    "userID": "61581545831408",
    "name": "Kim Sumaiya",
    "gender": 1,
    "vanity": "",
    "exp": 1,
    "money": 0,
    "banned": {},
    "settings": {},
    "data": {},
    "createdAt": "2025-10-20T01:12:05.590Z",
    "updatedAt": "2025-10-20T01:12:05.656Z"
  },
  {
    "userID": "61573877080039",
    "name": "mim",
    "gender": 2,
    "vanity": "soha.khan.257466",
    "exp": 2,
    "money": 0,
    "banned": {},
    "settings": {},
    "data": {},
    "createdAt": "2025-10-20T01:42:55.333Z",
    "updatedAt": "2025-10-20T01:42:58.061Z"
  },
  {
    "userID": "61580427970685",
    "name": "Israt Tahsin Taha",
    "gender": 1,
    "vanity": "isaratatahasinataha",
    "exp": 4,
    "money": 0,
    "banned": {},
    "settings": {},
    "data": {},
    "createdAt": "2025-10-20T01:53:51.346Z",
    "updatedAt": "2025-10-20T06:03:25.359Z"
  },
  {
    "userID": "61568786700177",
    "name": "Nipa Akter",
    "gender": 2,
    "vanity": "sara.mony.228461",
    "exp": 169,
    "money": 0,
    "banned": {},
    "settings": {},
    "data": {},
    "createdAt": "2025-10-20T02:02:30.121Z",
    "updatedAt": "2025-10-20T06:56:46.163Z"
  },
  {
    "userID": "61574683731003",
    "name": "Ziniya Ishara",
    "gender": 2,
    "vanity": "Ziniya.zara.13579",
    "exp": 0,
    "money": 0,
    "banned": {},
    "settings": {},
    "data": {},
    "updatedAt": "2025-10-20T02:13:48.053Z",
    "createdAt": "2025-10-20T02:13:48.053Z"
  },
  {
    "userID": "61554158934577",
    "name": "মারিয়া ",
    "gender": 2,
    "vanity": "mariya.302647",
    "exp": 20,
    "money": 0,
    "banned": {},
    "settings": {},
    "data": {},
    "createdAt": "2025-10-20T02:20:22.154Z",
    "updatedAt": "2025-10-20T07:02:31.130Z"
  },
  {
    "userID": "100090834158469",
    "name": "Ratul Kln",
    "gender": 2,
    "vanity": "ratulkln",
    "exp": 1,
    "money": 0,
    "banned": {},
    "settings": {},
    "data": {},
    "createdAt": "2025-10-20T02:25:19.065Z",
    "updatedAt": "2025-10-20T02:25:19.088Z"
  },
  {
    "userID": "61550032983043",
    "name": "Xiu San Yui Hiroki",
    "gender": 2,
    "vanity": "xiu.san.yui.hiroki",
    "exp": 1,
    "money": 0,
    "banned": {},
    "settings": {},
    "data": {},
    "createdAt": "2025-10-20T02:31:03.229Z",
    "updatedAt": "2025-10-20T02:31:03.459Z"
  },
  {
    "userID": "61566911566075",
    "name": "Sumaiya Akthar",
    "gender": 1,
    "vanity": "sumaiya.akther.sumaiya.akther.13001",
    "exp": 9,
    "money": 0,
    "banned": {},
    "settings": {},
    "data": {},
    "createdAt": "2025-10-20T02:34:54.103Z",
    "updatedAt": "2025-10-20T02:38:34.961Z"
  },
  {
    "userID": "61582141469003",
    "name": "ই্স্টুঁ পি্ড্ঁ─🥵💋💦👅󱢏",
    "gender": 1,
    "vanity": "",
    "exp": 2,
    "money": 0,
    "banned": {},
    "settings": {},
    "data": {},
    "createdAt": "2025-10-20T02:58:13.906Z",
    "updatedAt": "2025-10-20T03:04:39.415Z"
  },
  {
    "userID": "61572419034788",
    "name": "Xe'z Alv'ee",
    "gender": 2,
    "vanity": "xe.z.alv.ee",
    "exp": 1,
    "money": 0,
    "banned": {},
    "settings": {},
    "data": {},
    "createdAt": "2025-10-20T03:11:48.156Z",
    "updatedAt": "2025-10-20T03:11:57.558Z"
  },
  {
    "userID": "61577048952149",
    "name": "Mst Sampia Begum",
    "gender": 1,
    "vanity": "",
    "exp": 34,
    "money": 0,
    "banned": {},
    "settings": {},
    "data": {},
    "createdAt": "2025-10-20T03:17:07.423Z",
    "updatedAt": "2025-10-20T03:41:49.455Z"
  },
  {
    "userID": "100046621336702",
    "name": "Ew'r Ayan",
    "gender": 2,
    "vanity": "sami.islam.424008",
    "exp": 4,
    "money": 0,
    "banned": {},
    "settings": {},
    "data": {},
    "createdAt": "2025-10-20T03:21:40.678Z",
    "updatedAt": "2025-10-20T06:48:37.899Z"
  },
  {
    "userID": "61565657995263",
    "name": "Ananya Ara Anu",
    "gender": 1,
    "vanity": "ananya.anu.179818",
    "exp": 31,
    "money": 0,
    "banned": {},
    "settings": {},
    "data": {},
    "createdAt": "2025-10-20T03:24:10.686Z",
    "updatedAt": "2025-10-20T05:00:18.447Z"
  },
  {
    "userID": "61555485656526",
    "name": "Ît's Šhïzûkå",
    "gender": 1,
    "vanity": "it.s.shizuka.877284",
    "exp": 6,
    "money": 0,
    "banned": {},
    "settings": {},
    "data": {},
    "createdAt": "2025-10-20T03:31:22.457Z",
    "updatedAt": "2025-10-20T03:33:30.626Z"
  },
  {
    "userID": "100035686872506",
    "name": "Engr Earfan",
    "gender": 1,
    "vanity": "asha.amarvalobasha.50",
    "exp": 8,
    "money": 0,
    "banned": {},
    "settings": {},
    "data": {},
    "createdAt": "2025-10-20T03:49:17.137Z",
    "updatedAt": "2025-10-20T06:59:37.322Z"
  },
  {
    "userID": "61578044363881",
    "name": "Uçhîhà Vai",
    "gender": 2,
    "vanity": "zeynoxi7",
    "exp": 468,
    "money": 0,
    "banned": {},
    "settings": {},
    "data": {},
    "createdAt": "2025-10-20T03:52:53.636Z",
    "updatedAt": "2025-10-20T06:58:18.390Z"
  },
  {
    "userID": "61570470666136",
    "name": "Af Rin",
    "gender": 1,
    "vanity": "afrin.akter.443318",
    "exp": 114,
    "money": 0,
    "banned": {},
    "settings": {},
    "data": {},
    "createdAt": "2025-10-20T03:52:55.756Z",
    "updatedAt": "2025-10-20T06:30:33.370Z"
  },
  {
    "userID": "61573927470056",
    "name": "Ma Ki Ma",
    "gender": 1,
    "vanity": "",
    "exp": 2,
    "money": 0,
    "banned": {},
    "settings": {},
    "data": {},
    "createdAt": "2025-10-20T03:53:06.734Z",
    "updatedAt": "2025-10-20T03:55:48.122Z"
  },
  {
    "userID": "61581650498062",
    "name": "Itachi Jr II",
    "gender": 2,
    "vanity": "",
    "exp": 160,
    "money": 0,
    "banned": {},
    "settings": {},
    "data": {},
    "createdAt": "2025-10-20T03:53:15.613Z",
    "updatedAt": "2025-10-20T06:56:04.783Z"
  },
  {
    "userID": "61581799858592",
    "name": "Fa Riya",
    "gender": 1,
    "vanity": "",
    "exp": 9,
    "money": 0,
    "banned": {},
    "settings": {},
    "data": {},
    "createdAt": "2025-10-20T03:53:24.314Z",
    "updatedAt": "2025-10-20T04:25:57.957Z"
  },
  {
    "userID": "100089759331929",
    "name": "Obito Uchiiha",
    "gender": 2,
    "vanity": "hujaifa.be.bee",
    "exp": 12,
    "money": 0,
    "banned": {},
    "settings": {},
    "data": {},
    "createdAt": "2025-10-20T03:53:47.984Z",
    "updatedAt": "2025-10-20T04:34:48.792Z"
  },
  {
    "userID": "61550196133343",
    "name": "TO N NI",
    "gender": 1,
    "vanity": "",
    "exp": 2,
    "money": 0,
    "banned": {},
    "settings": {},
    "data": {},
    "createdAt": "2025-10-20T03:53:52.826Z",
    "updatedAt": "2025-10-20T03:54:47.499Z"
  },
  {
    "userID": "61580395656769",
    "name": "Natsumi akira",
    "gender": 1,
    "vanity": "itzzzmeprecious",
    "exp": 1,
    "money": 0,
    "banned": {},
    "settings": {},
    "data": {},
    "createdAt": "2025-10-20T03:54:12.815Z",
    "updatedAt": "2025-10-20T03:54:12.856Z"
  },
  {
    "userID": "100081165530122",
    "name": "Ashikur Rahman Akash",
    "gender": 2,
    "vanity": "ashikur.rahman.akash.443641",
    "exp": 1,
    "money": 0,
    "banned": {},
    "settings": {},
    "data": {},
    "createdAt": "2025-10-20T03:55:19.388Z",
    "updatedAt": "2025-10-20T03:55:19.404Z"
  },
  {
    "userID": "61556271386287",
    "name": "Jiraiya Sama",
    "gender": 2,
    "vanity": "",
    "exp": 25,
    "money": 0,
    "banned": {},
    "settings": {},
    "data": {},
    "createdAt": "2025-10-20T03:55:50.533Z",
    "updatedAt": "2025-10-20T06:52:26.589Z"
  },
  {
    "userID": "61582442937509",
    "name": "Eren Restricted II",
    "gender": 2,
    "vanity": "",
    "exp": 0,
    "money": 0,
    "banned": {},
    "settings": {},
    "data": {},
    "updatedAt": "2025-10-20T03:55:59.210Z",
    "createdAt": "2025-10-20T03:55:59.210Z"
  },
  {
    "userID": "61581964090250",
    "name": "Luminara Silvexis II",
    "gender": 1,
    "vanity": "",
    "exp": 32,
    "money": 0,
    "banned": {},
    "settings": {},
    "data": {},
    "createdAt": "2025-10-20T03:56:24.694Z",
    "updatedAt": "2025-10-20T05:17:47.066Z"
  },
  {
    "userID": "61581663113989",
    "name": "Vortex Savagery Era",
    "gender": 2,
    "vanity": "vortextorabbu",
    "exp": 76,
    "money": 0,
    "banned": {},
    "settings": {},
    "data": {},
    "createdAt": "2025-10-20T03:57:12.917Z",
    "updatedAt": "2025-10-20T06:39:12.459Z"
  },
  {
    "userID": "100065285601851",
    "name": "Asifur Rahman",
    "gender": 2,
    "vanity": "asifur.rahman.shoaib.2024",
    "exp": 38,
    "money": 0,
    "banned": {},
    "settings": {},
    "data": {},
    "createdAt": "2025-10-20T04:00:48.583Z",
    "updatedAt": "2025-10-20T05:05:40.108Z"
  },
  {
    "userID": "61581520397546",
    "name": "Jessica Filandez",
    "gender": 1,
    "vanity": "",
    "exp": 1,
    "money": 0,
    "banned": {},
    "settings": {},
    "data": {},
    "createdAt": "2025-10-20T04:01:09.381Z",
    "updatedAt": "2025-10-20T04:01:09.418Z"
  },
  {
    "userID": "61578650897440",
    "name": "HP Minu",
    "gender": 1,
    "vanity": "",
    "exp": 16,
    "money": 0,
    "banned": {},
    "settings": {},
    "data": {},
    "createdAt": "2025-10-20T04:04:57.148Z",
    "updatedAt": "2025-10-20T06:12:42.805Z"
  },
  {
    "userID": "61552444333825",
    "name": "Nafsu Afa",
    "gender": 1,
    "vanity": "",
    "exp": 26,
    "money": 0,
    "banned": {},
    "settings": {},
    "data": {},
    "createdAt": "2025-10-20T04:07:11.643Z",
    "updatedAt": "2025-10-20T06:17:12.896Z"
  },
  {
    "userID": "61581288478856",
    "name": "Hina Ta",
    "gender": 1,
    "vanity": "",
    "exp": 87,
    "money": 0,
    "banned": {},
    "settings": {},
    "data": {},
    "createdAt": "2025-10-20T04:11:54.902Z",
    "updatedAt": "2025-10-20T06:43:33.956Z"
  },
  {
    "userID": "100090450434388",
    "name": "Itachi Uchi Ha",
    "gender": 2,
    "vanity": "byartha.kabi.116317",
    "exp": 2,
    "money": 0,
    "banned": {},
    "settings": {},
    "data": {},
    "createdAt": "2025-10-20T04:12:46.176Z",
    "updatedAt": "2025-10-20T04:13:05.460Z"
  },
  {
    "userID": "100094058468145",
    "name": "Ft Tonu Siz",
    "gender": 1,
    "vanity": "is.takia.islam",
    "exp": 1,
    "money": 0,
    "banned": {},
    "settings": {},
    "data": {},
    "createdAt": "2025-10-20T04:20:10.006Z",
    "updatedAt": "2025-10-20T04:20:10.861Z"
  },
  {
    "userID": "100088292503910",
    "name": "SA KI B",
    "gender": 1,
    "vanity": "sa.ki.b.555909",
    "exp": 298,
    "money": 0,
    "banned": {},
    "settings": {},
    "data": {},
    "createdAt": "2025-10-20T04:20:25.616Z",
    "updatedAt": "2025-10-20T07:02:11.056Z"
  },
  {
    "userID": "61561674475784",
    "name": "Jannatul Sumaiya",
    "gender": 1,
    "vanity": "sumaiya.jannat.jeba.2025",
    "exp": 56,
    "money": 0,
    "banned": {},
    "settings": {},
    "data": {},
    "createdAt": "2025-10-20T04:20:41.934Z",
    "updatedAt": "2025-10-20T06:08:20.661Z"
  },
  {
    "userID": "61581998498188",
    "name": "Itz TasNîya",
    "gender": 1,
    "vanity": "",
    "exp": 0,
    "money": 0,
    "banned": {},
    "settings": {},
    "data": {},
    "updatedAt": "2025-10-20T04:20:50.820Z",
    "createdAt": "2025-10-20T04:20:50.820Z"
  },
  {
    "userID": "61582403992562",
    "name": "Vortex L. Ra'fu",
    "gender": 2,
    "vanity": "",
    "exp": 6,
    "money": 0,
    "banned": {},
    "settings": {},
    "data": {},
    "createdAt": "2025-10-20T04:28:53.162Z",
    "updatedAt": "2025-10-20T05:09:23.479Z"
  },
  {
    "userID": "100090404713116",
    "name": "Moŋɩʀ Sʜʌʀɩʆ",
    "gender": 2,
    "vanity": "mo.s.359551",
    "exp": 5,
    "money": 0,
    "banned": {},
    "settings": {},
    "data": {},
    "createdAt": "2025-10-20T04:29:22.068Z",
    "updatedAt": "2025-10-20T04:59:43.437Z"
  },
  {
    "userID": "61582092421164",
    "name": "Sha Hin",
    "gender": 2,
    "vanity": "",
    "exp": 0,
    "money": 0,
    "banned": {},
    "settings": {},
    "data": {},
    "updatedAt": "2025-10-20T04:31:37.134Z",
    "createdAt": "2025-10-20T04:31:37.134Z"
  },
  {
    "userID": "61556222080156",
    "name": "Habiba Khan",
    "gender": 1,
    "vanity": "habiba.khan.363582",
    "exp": 35,
    "money": 0,
    "banned": {},
    "settings": {},
    "data": {},
    "createdAt": "2025-10-20T04:33:07.280Z",
    "updatedAt": "2025-10-20T06:28:54.977Z"
  },
  {
    "userID": "61576194522167",
    "name": "Jara Islam",
    "gender": 1,
    "vanity": "",
    "exp": 1,
    "money": 0,
    "banned": {},
    "settings": {},
    "data": {},
    "createdAt": "2025-10-20T04:35:27.807Z",
    "updatedAt": "2025-10-20T04:35:27.821Z"
  },
  {
    "userID": "100043110469175",
    "name": "Parapti Khanom",
    "gender": 2,
    "vanity": "abidur.rahman.125167",
    "exp": 0,
    "money": 0,
    "banned": {},
    "settings": {},
    "data": {},
    "updatedAt": "2025-10-20T04:42:22.477Z",
    "createdAt": "2025-10-20T04:42:22.477Z"
  },
  {
    "userID": "61562600571698",
    "name": "Mis Sadiya Nusrat Imroj",
    "gender": 1,
    "vanity": "",
    "exp": 187,
    "money": 0,
    "banned": {},
    "settings": {},
    "data": {},
    "createdAt": "2025-10-20T04:49:34.513Z",
    "updatedAt": "2025-10-20T06:52:00.984Z"
  },
  {
    "userID": "61550290800171",
    "name": "Jahidul Islam",
    "gender": 2,
    "vanity": "",
    "exp": 30,
    "money": 0,
    "banned": {},
    "settings": {},
    "data": {},
    "createdAt": "2025-10-20T04:49:44.266Z",
    "updatedAt": "2025-10-20T05:05:41.556Z"
  },
  {
    "userID": "61558581505830",
    "name": "Ritu Mitu",
    "gender": 1,
    "vanity": "ritu.mitu.192676",
    "exp": 6,
    "money": 0,
    "banned": {},
    "settings": {},
    "data": {},
    "createdAt": "2025-10-20T04:51:41.000Z",
    "updatedAt": "2025-10-20T04:52:53.655Z"
  },
  {
    "userID": "61581472436580",
    "name": "Rohan Mollic'k",
    "gender": 1,
    "vanity": "",
    "exp": 15,
    "money": 0,
    "banned": {},
    "settings": {},
    "data": {},
    "createdAt": "2025-10-20T04:54:26.668Z",
    "updatedAt": "2025-10-20T06:53:40.862Z"
  },
  {
    "userID": "61581502015227",
    "name": "Muntasir Mahmud",
    "gender": 2,
    "vanity": "ibonex.eden",
    "exp": 8,
    "money": 0,
    "banned": {},
    "settings": {},
    "data": {},
    "createdAt": "2025-10-20T04:54:31.350Z",
    "updatedAt": "2025-10-20T06:12:33.911Z"
  },
  {
    "userID": "61558236604061",
    "name": "Parvez Islam",
    "gender": 2,
    "vanity": "parvez.mal.s.2025",
    "exp": 1,
    "money": 0,
    "banned": {},
    "settings": {},
    "data": {},
    "createdAt": "2025-10-20T04:54:34.962Z",
    "updatedAt": "2025-10-20T04:54:35.155Z"
  },
  {
    "userID": "61579851374343",
    "name": "Mi Ka Sa",
    "gender": 1,
    "vanity": "",
    "exp": 2,
    "money": 0,
    "banned": {},
    "settings": {},
    "data": {},
    "createdAt": "2025-10-20T04:59:47.909Z",
    "updatedAt": "2025-10-20T05:00:01.441Z"
  },
  {
    "userID": "61581056446563",
    "name": "Aiko Adiya",
    "gender": 1,
    "vanity": "",
    "exp": 1,
    "money": 0,
    "banned": {},
    "settings": {},
    "data": {},
    "createdAt": "2025-10-20T05:01:33.328Z",
    "updatedAt": "2025-10-20T05:01:33.357Z"
  },
  {
    "userID": "61581707442759",
    "name": "Tanjiro Kamado",
    "gender": 2,
    "vanity": "",
    "exp": 1,
    "money": 0,
    "banned": {},
    "settings": {},
    "data": {},
    "createdAt": "2025-10-20T05:03:14.911Z",
    "updatedAt": "2025-10-20T05:03:14.922Z"
  },
  {
    "userID": "61575814054219",
    "name": "Zara Islam",
    "gender": 1,
    "vanity": "",
    "exp": 0,
    "money": 0,
    "banned": {},
    "settings": {},
    "data": {},
    "updatedAt": "2025-10-20T05:06:27.847Z",
    "createdAt": "2025-10-20T05:06:27.847Z"
  },
  {
    "userID": "61552204916573",
    "name": "Painful Sun",
    "gender": 2,
    "vanity": "painful.sun.2025",
    "exp": 1,
    "money": 0,
    "banned": {},
    "settings": {},
    "data": {},
    "createdAt": "2025-10-20T05:12:52.669Z",
    "updatedAt": "2025-10-20T05:12:52.695Z"
  },
  {
    "userID": "100038237238500",
    "name": "Md Seam Hassan",
    "gender": 2,
    "vanity": "mdseam.hassan.98",
    "exp": 120,
    "money": 0,
    "banned": {},
    "settings": {},
    "data": {},
    "createdAt": "2025-10-20T05:13:06.267Z",
    "updatedAt": "2025-10-20T07:01:23.158Z"
  },
  {
    "userID": "61580516897141",
    "name": "EN Emon",
    "gender": 2,
    "vanity": "",
    "exp": 9,
    "money": 0,
    "banned": {},
    "settings": {},
    "data": {},
    "createdAt": "2025-10-20T05:15:57.462Z",
    "updatedAt": "2025-10-20T06:56:48.558Z"
  },
  {
    "userID": "100089734003480",
    "name": "Madhurjo Hossain",
    "gender": 2,
    "vanity": "",
    "exp": 3,
    "money": 0,
    "banned": {},
    "settings": {},
    "data": {},
    "createdAt": "2025-10-20T05:16:13.851Z",
    "updatedAt": "2025-10-20T05:30:11.044Z"
  },
  {
    "userID": "61575247891182",
    "name": "Jannatul Sumaiya",
    "gender": 1,
    "vanity": "jannatul.sumaiya.936374",
    "exp": 14,
    "money": 0,
    "banned": {},
    "settings": {},
    "data": {},
    "createdAt": "2025-10-20T05:17:32.467Z",
    "updatedAt": "2025-10-20T05:59:19.864Z"
  },
  {
    "userID": "61572696635661",
    "name": "Sumi Banik",
    "gender": 1,
    "vanity": "sumi.banik.478299",
    "exp": 3,
    "money": 0,
    "banned": {},
    "settings": {},
    "data": {},
    "createdAt": "2025-10-20T05:19:43.830Z",
    "updatedAt": "2025-10-20T05:36:49.866Z"
  },
  {
    "userID": "61580644379525",
    "name": "Nabila Islam Ilma",
    "gender": 1,
    "vanity": "",
    "exp": 2,
    "money": 0,
    "banned": {},
    "settings": {},
    "data": {},
    "createdAt": "2025-10-20T05:21:07.695Z",
    "updatedAt": "2025-10-20T06:54:33.782Z"
  },
  {
    "userID": "100093534096296",
    "name": "Sadman Hyder",
    "gender": 2,
    "vanity": "sadman.hyder.2024",
    "exp": 1,
    "money": 0,
    "banned": {},
    "settings": {},
    "data": {},
    "createdAt": "2025-10-20T05:22:59.509Z",
    "updatedAt": "2025-10-20T05:22:59.524Z"
  },
  {
    "userID": "61564248022453",
    "name": "NoWshin AiRa",
    "gender": 1,
    "vanity": "jeon.nusu.09",
    "exp": 42,
    "money": 0,
    "banned": {},
    "settings": {},
    "data": {},
    "createdAt": "2025-10-20T05:23:55.671Z",
    "updatedAt": "2025-10-20T06:49:35.278Z"
  },
  {
    "userID": "61581777921552",
    "name": "Sumaiya Nilima",
    "gender": 1,
    "vanity": "",
    "exp": 1,
    "money": 0,
    "banned": {},
    "settings": {},
    "data": {},
    "createdAt": "2025-10-20T05:26:35.414Z",
    "updatedAt": "2025-10-20T05:26:35.429Z"
  },
  {
    "userID": "61582295651920",
    "name": "Nocthyrax T. Zeqeuidonelmorathionidraxion",
    "gender": 2,
    "vanity": "",
    "exp": 5,
    "money": 0,
    "banned": {},
    "settings": {},
    "data": {},
    "createdAt": "2025-10-20T05:28:35.075Z",
    "updatedAt": "2025-10-20T05:37:47.043Z"
  },
  {
    "userID": "61581759767819",
    "name": "Israfil Hossen",
    "gender": 2,
    "vanity": "",
    "exp": 0,
    "money": 0,
    "banned": {},
    "settings": {},
    "data": {},
    "updatedAt": "2025-10-20T05:28:47.699Z",
    "createdAt": "2025-10-20T05:28:47.699Z"
  },
  {
    "userID": "61581331756796",
    "name": "আরিফুল ইসলাম সাঈদ",
    "gender": 1,
    "vanity": "",
    "exp": 2,
    "money": 0,
    "banned": {},
    "settings": {},
    "data": {},
    "createdAt": "2025-10-20T05:30:18.144Z",
    "updatedAt": "2025-10-20T05:31:32.455Z"
  },
  {
    "userID": "61578610826390",
    "name": "Ewr Maya",
    "gender": 1,
    "vanity": "flowery42",
    "exp": 2,
    "money": 0,
    "banned": {},
    "settings": {},
    "data": {},
    "createdAt": "2025-10-20T05:30:30.966Z",
    "updatedAt": "2025-10-20T05:32:21.683Z"
  },
  {
    "userID": "61582208553737",
    "name": "Aria Na",
    "gender": 1,
    "vanity": "",
    "exp": 26,
    "money": 0,
    "banned": {},
    "settings": {},
    "data": {},
    "createdAt": "2025-10-20T05:42:16.232Z",
    "updatedAt": "2025-10-20T05:54:33.056Z"
  },
  {
    "userID": "61553754787731",
    "name": "Mst Tasmin Aktar",
    "gender": 1,
    "vanity": "mst.tasmin.aktar.370526",
    "exp": 0,
    "money": 0,
    "banned": {},
    "settings": {},
    "data": {},
    "updatedAt": "2025-10-20T05:47:02.561Z",
    "createdAt": "2025-10-20T05:47:02.561Z"
  },
  {
    "userID": "100083579353024",
    "name": "DRD",
    "gender": 2,
    "vanity": "drd.890559",
    "exp": 13,
    "money": 0,
    "banned": {},
    "settings": {},
    "data": {},
    "createdAt": "2025-10-20T05:47:55.038Z",
    "updatedAt": "2025-10-20T07:01:04.251Z"
  },
  {
    "userID": "100088554251911",
    "name": "Md Biraj",
    "gender": 2,
    "vanity": "md.biraj.375109",
    "exp": 1,
    "money": 0,
    "banned": {},
    "settings": {},
    "data": {},
    "createdAt": "2025-10-20T05:56:10.854Z",
    "updatedAt": "2025-10-20T05:56:10.958Z"
  },
  {
    "userID": "61577718200665",
    "name": "New Gojo",
    "gender": 2,
    "vanity": "mistergojo10",
    "exp": 8,
    "money": 0,
    "banned": {},
    "settings": {},
    "data": {},
    "createdAt": "2025-10-20T05:59:49.407Z",
    "updatedAt": "2025-10-20T06:30:02.568Z"
  },
  {
    "userID": "61581808956963",
    "name": "Vortex L. Rio",
    "gender": 2,
    "vanity": "superiorriotoderabburabbuh",
    "exp": 3,
    "money": 0,
    "banned": {},
    "settings": {},
    "data": {},
    "createdAt": "2025-10-20T05:59:56.604Z",
    "updatedAt": "2025-10-20T06:00:15.700Z"
  },
  {
    "userID": "100093417186819",
    "name": "Md Najrul Islam",
    "gender": 2,
    "vanity": "",
    "exp": 42,
    "money": 0,
    "banned": {},
    "settings": {},
    "data": {},
    "createdAt": "2025-10-20T06:05:38.960Z",
    "updatedAt": "2025-10-20T07:02:03.360Z"
  },
  {
    "userID": "61582180317312",
    "name": "Alya Chan",
    "gender": 1,
    "vanity": "alya.chan.624847",
    "exp": 4,
    "money": 0,
    "banned": {},
    "settings": {},
    "data": {},
    "createdAt": "2025-10-20T06:06:52.964Z",
    "updatedAt": "2025-10-20T06:08:43.956Z"
  },
  {
    "userID": "100076563636696",
    "name": "Sîñglē Mãñ",
    "gender": 2,
    "vanity": "",
    "exp": 3,
    "money": 0,
    "banned": {},
    "settings": {},
    "data": {},
    "createdAt": "2025-10-20T06:09:04.955Z",
    "updatedAt": "2025-10-20T06:14:40.333Z"
  },
  {
    "userID": "61572180419361",
    "name": "Arick Bb'z",
    "gender": 2,
    "vanity": "nobita.nobi.762876",
    "exp": 1,
    "money": 0,
    "banned": {},
    "settings": {},
    "data": {},
    "createdAt": "2025-10-20T06:11:56.256Z",
    "updatedAt": "2025-10-20T06:11:56.278Z"
  },
  {
    "userID": "61559742608432",
    "name": "Sinthiya Ahmed",
    "gender": 1,
    "vanity": "tanha.akter.tasmim.2024",
    "exp": 8,
    "money": 0,
    "banned": {},
    "settings": {},
    "data": {},
    "createdAt": "2025-10-20T06:12:57.634Z",
    "updatedAt": "2025-10-20T06:56:38.814Z"
  },
  {
    "userID": "61582288613548",
    "name": "Sho B Nom",
    "gender": 1,
    "vanity": "",
    "exp": 1,
    "money": 0,
    "banned": {},
    "settings": {},
    "data": {},
    "createdAt": "2025-10-20T06:23:43.883Z",
    "updatedAt": "2025-10-20T06:23:43.907Z"
  },
  {
    "userID": "61551055922867",
    "name": "নিঁজুঁমঁ রাঁতেঁরঁ পঁরীঁ",
    "gender": 1,
    "vanity": "nimjummam.ramtemram.pamrim.960102",
    "exp": 2,
    "money": 0,
    "banned": {},
    "settings": {},
    "data": {},
    "createdAt": "2025-10-20T06:33:49.284Z",
    "updatedAt": "2025-10-20T06:36:41.180Z"
  },
  {
    "userID": "61565397302828",
    "name": "Adiba Nusrat",
    "gender": 1,
    "vanity": "adiba.nusrat.626130",
    "exp": 1,
    "money": 0,
    "banned": {},
    "settings": {},
    "data": {},
    "createdAt": "2025-10-20T06:35:05.143Z",
    "updatedAt": "2025-10-20T06:35:05.163Z"
  },
  {
    "userID": "100045122107250",
    "name": "হেমন্ত কাল",
    "gender": 1,
    "vanity": "",
    "exp": 0,
    "money": 0,
    "banned": {},
    "settings": {},
    "data": {},
    "updatedAt": "2025-10-20T06:37:01.610Z",
    "createdAt": "2025-10-20T06:37:01.610Z"
  },
  {
    "userID": "61578107853074",
    "name": "Kim Tan",
    "gender": 1,
    "vanity": "",
    "exp": 2,
    "money": 0,
    "banned": {},
    "settings": {},
    "data": {},
    "createdAt": "2025-10-20T06:37:06.037Z",
    "updatedAt": "2025-10-20T06:37:23.328Z"
  },
  {
    "userID": "100037922232369",
    "name": "Nadira Begum",
    "gender": 1,
    "vanity": "nadira.begum.921230",
    "exp": 9,
    "money": 0,
    "banned": {},
    "settings": {},
    "data": {},
    "createdAt": "2025-10-20T06:37:34.752Z",
    "updatedAt": "2025-10-20T06:58:43.960Z"
  },
  {
    "userID": "61560863114631",
    "name": "Ahemd Rafin",
    "gender": 2,
    "vanity": "ahemd.rafin",
    "exp": 1,
    "money": 0,
    "banned": {},
    "settings": {},
    "data": {},
    "createdAt": "2025-10-20T06:38:17.102Z",
    "updatedAt": "2025-10-20T06:38:17.225Z"
  },
  {
    "userID": "61578320948540",
    "name": "Mahin Ahmed",
    "gender": 1,
    "vanity": "Mahin.ghumacche0",
    "exp": 2,
    "money": 0,
    "banned": {},
    "settings": {},
    "data": {},
    "createdAt": "2025-10-20T06:38:30.340Z",
    "updatedAt": "2025-10-20T06:38:41.758Z"
  },
  {
    "userID": "61566141910135",
    "name": "Izumi Uchiha",
    "gender": 1,
    "vanity": "fahyma.akhtar",
    "exp": 3,
    "money": 0,
    "banned": {},
    "settings": {},
    "data": {},
    "createdAt": "2025-10-20T06:40:10.470Z",
    "updatedAt": "2025-10-20T06:43:43.034Z"
  },
  {
    "userID": "61576216496782",
    "name": "Raha Islam Raha",
    "gender": 1,
    "vanity": "raha.islam.raha.355916",
    "exp": 2,
    "money": 0,
    "banned": {},
    "settings": {},
    "data": {},
    "createdAt": "2025-10-20T06:43:09.477Z",
    "updatedAt": "2025-10-20T06:44:10.712Z"
  },
  {
    "userID": "61581420003800",
    "name": "Wraithridge Zara Moni",
    "gender": 1,
    "vanity": "",
    "exp": 6,
    "money": 0,
    "banned": {},
    "settings": {},
    "data": {},
    "createdAt": "2025-10-20T06:52:07.108Z",
    "updatedAt": "2025-10-20T06:59:59.257Z"
  },
  {
    "userID": "61582626146497",
    "name": "Nocthyrax T. AbyssLord Vynar",
    "gender": 2,
    "vanity": "",
    "exp": 8,
    "money": 0,
    "banned": {},
    "settings": {},
    "data": {},
    "createdAt": "2025-10-20T06:57:05.437Z",
    "updatedAt": "2025-10-20T07:02:14.176Z"
  }
]